FigureGenerator/__init__.py
FigureGenerator/screenshot_maker.py
FigureGenerator/utils.py
FigureGenerator/version.py
figuregenerator-0.0.5.data/scripts/figure_generator
figuregenerator-0.0.5.dist-info/licenses/LICENSE
figuregenerator-0.0.5.dist-info/METADATA
figuregenerator-0.0.5.dist-info/WHEEL
figuregenerator-0.0.5.dist-info/top_level.txt
figuregenerator-0.0.5.dist-info/RECORD
