Metadata-Version: 2.4
Name: FigureGenerator
Version: 0.0.5
Summary: Making screenshots for presentations and manuscripts.
Home-page: https://github.com/CBICA/FigureGenerator
Author: Sarthak Pati
Author-email: software@cbica.upenn.edu
License: BSD-3-Clause License
Keywords: medical-imaging,screenshot,figure-generator,publication
Classifier: Development Status :: 1 - Planning
Classifier: Intended Audience :: Science/Research
Classifier: License :: OSI Approved :: BSD License
Classifier: Natural Language :: English
Classifier: Operating System :: OS Independent
Classifier: Programming Language :: Python :: 3.10
Classifier: Programming Language :: Python :: 3.11
Classifier: Programming Language :: Python :: 3.12
Requires-Python: >=3.9
License-File: LICENSE
Requires-Dist: numpy>=1.19.2
Requires-Dist: SimpleITK!=2.0.*
Requires-Dist: SimpleITK!=2.2.1
Requires-Dist: pytest
Requires-Dist: coverage
Requires-Dist: psutil
Requires-Dist: black
Requires-Dist: matplotlib
Requires-Dist: requests
Requires-Dist: setuptools
Dynamic: author
Dynamic: author-email
Dynamic: classifier
Dynamic: description
Dynamic: description-content-type
Dynamic: home-page
Dynamic: keywords
Dynamic: license
Dynamic: license-file
Dynamic: requires-dist
Dynamic: requires-python
Dynamic: summary
